asynq/__init__.py
asynq/__init__.pyi
asynq/_debug.cp310-win_amd64.pyd
asynq/_debug.pxd
asynq/_debug.py
asynq/_debug.pyi
asynq/async_task.cp310-win_amd64.pyd
asynq/async_task.pxd
asynq/async_task.py
asynq/async_task.pyi
asynq/asynq_to_async.cp310-win_amd64.pyd
asynq/asynq_to_async.pxd
asynq/asynq_to_async.py
asynq/batching.cp310-win_amd64.pyd
asynq/batching.pxd
asynq/batching.py
asynq/batching.pyi
asynq/contexts.cp310-win_amd64.pyd
asynq/contexts.pxd
asynq/contexts.py
asynq/contexts.pyi
asynq/debug.py
asynq/debug.pyi
asynq/decorators.cp310-win_amd64.pyd
asynq/decorators.pxd
asynq/decorators.py
asynq/decorators.pyi
asynq/futures.cp310-win_amd64.pyd
asynq/futures.pxd
asynq/futures.py
asynq/futures.pyi
asynq/generator.py
asynq/generator.pyi
asynq/mock_.py
asynq/mock_.pyi
asynq/profiler.cp310-win_amd64.pyd
asynq/profiler.pxd
asynq/profiler.py
asynq/profiler.pyi
asynq/py.typed
asynq/scheduler.cp310-win_amd64.pyd
asynq/scheduler.pxd
asynq/scheduler.py
asynq/scheduler.pyi
asynq/scoped_value.cp310-win_amd64.pyd
asynq/scoped_value.pxd
asynq/scoped_value.py
asynq/scoped_value.pyi
asynq/tools.py
asynq/tools.pyi
asynq/utils.cp310-win_amd64.pyd
asynq/utils.pxd
asynq/utils.py
asynq/utils.pyi
asynq/tests/__init__.py
asynq/tests/caching.py
asynq/tests/debug_cache.py
asynq/tests/helpers.py
asynq/tests/test_active_task.py
asynq/tests/test_async_task.py
asynq/tests/test_asynq_to_async.py
asynq/tests/test_base.py
asynq/tests/test_batching.py
asynq/tests/test_channels.py
asynq/tests/test_contexts.py
asynq/tests/test_debug.py
asynq/tests/test_decorators.py
asynq/tests/test_exceptions.py
asynq/tests/test_futures.py
asynq/tests/test_generator.py
asynq/tests/test_mock.py
asynq/tests/test_multiple_inheritance.py
asynq/tests/test_performance.py
asynq/tests/test_profiler.py
asynq/tests/test_pyright.py
asynq/tests/test_recursion.py
asynq/tests/test_recursive_task.py
asynq/tests/test_scoped_value.py
asynq/tests/test_tools.py
asynq/tests/test_typing.py
asynq/tests/test_utils.py
asynq-1.6.0.dist-info/LICENSE
asynq-1.6.0.dist-info/METADATA
asynq-1.6.0.dist-info/WHEEL
asynq-1.6.0.dist-info/top_level.txt
asynq-1.6.0.dist-info/RECORD
