Metadata-Version: 2.1
Name: asynq
Version: 1.6.0
Summary: Quora's asynq library
Home-page: https://github.com/quora/asynq
Author: Quora, Inc.
Author-email: asynq@quora.com
License: Apache Software License
Keywords: quora asynq common utility
Classifier: License :: OSI Approved :: Apache Software License
Classifier: Programming Language :: Python
Classifier: Programming Language :: Python :: 3.9
Classifier: Programming Language :: Python :: 3.10
Classifier: Programming Language :: Python :: 3.11
Classifier: Programming Language :: Python :: 3.12
Classifier: Programming Language :: Python :: 3.13
Requires-Python: >=3.9
License-File: LICENSE
Requires-Dist: qcore
Requires-Dist: pygments
